<?xml version="1.0" encoding="utf-16"?>
<BMapModel xmlns:xsi="http://www.w3.org/2001/XMLSchema-instance" xmlns:xsd="http://www.w3.org/2001/XMLSchema">
<Name>TestMap</Name>
<Width>20</Width>
<Height>20</Height>
<Hexes>
<string>0,0,0,0,0,0,0,0,0,0,0,0,0,0,0,0,0,0,0,0</string>
<string>0,0,0,0,0,0,0,0,0,0,0,0,0,0,0,0,0,0,0,0</string>
<string>1,1,0,1,0,0,0,0,0,0,0,0,0,0,0,0,0,0,0,0</string>
<string>1,1,1,1,1,1,0,0,0,0,0,0,0,0,0,0,0,0,0,0</string>
<string>0,0,0,0,1,1,1,1,0,0,0,0,0,0,0,0,0,0,0,0</string>
<string>0,0,0,0,0,0,1,1,0,0,0,0,0,0,0,0,0,0,0,0</string>
<string>0,0,0,0,0,0,1,1,1,0,0,0,0,0,0,0,0,0,0,0</string>
<string>0,0,0,0,0,0,0,0,0,0,0,0,0,0,0,0,0,0,0,0</string>
<string>0,0,0,0,0,0,0,0,0,0,0,0,0,0,0,0,0,0,0,0</string>
<string>0,0,0,0,0,0,0,0,0,0,0,1,1,1,1,1,0,0,0,0</string>
<string>0,0,0,0,0,0,0,0,0,1,1,1,1,1,1,1,1,0,0,0</string>
<string>0,1,1,1,0,0,0,0,1,1,1,0,0,0,0,0,0,0,0,0</string>
<string>0,0,1,1,1,0,1,1,1,1,1,0,0,0,0,0,0,0,0,0</string>
<string>0,1,1,1,0,0,0,1,1,1,0,0,0,0,0,0,0,0,0,0</string>
<string>0,0,0,0,0,0,0,0,0,0,0,0,0,0,0,0,0,0,0,0</string>
<string>0,0,0,0,0,0,0,0,0,0,0,0,0,0,0,0,0,0,0,0</string>
<string>0,0,0,0,0,0,0,0,0,0,0,0,0,0,0,0,0,0,0,0</string>
<string>0,0,0,0,0,0,0,0,0,0,0,0,0,0,0,0,0,0,0,0</string>
<string>0,0,0,0,0,0,0,0,0,0,0,0,0,0,0,0,0,0,0,0</string>
<string>0,0,0,0,0,0,0,0,0,0,0,0,0,0,0,0,0,0,0,0</string>
</Hexes>

<P1Starts>
<ModelCoordinate><X>1</X><Y>1</Y></ModelCoordinate>
<ModelCoordinate><X>1</X><Y>2</Y></ModelCoordinate>
<ModelCoordinate><X>1</X><Y>3</Y></ModelCoordinate>
<!--<ModelCoordinate><X>1</X><Y>4</Y></ModelCoordinate>
<ModelCoordinate><X>1</X><Y>5</Y></ModelCoordinate>-->
</P1Starts>

<P2Starts>
<ModelCoordinate><X>18</X><Y>14</Y></ModelCoordinate>
<ModelCoordinate><X>18</X><Y>15</Y></ModelCoordinate>
<ModelCoordinate><X>18</X><Y>16</Y></ModelCoordinate>
<!--<ModelCoordinate><X>18</X><Y>17</Y></ModelCoordinate>
<ModelCoordinate><X>18</X><Y>18</Y></ModelCoordinate>-->
</P2Starts>

</BMapModel>
